MANIFEST.in
README.rst
setup.py
doc/Makefile
doc/backprop.png
doc/conf.py
doc/dg_backprop.rst
doc/dg_todo.rst
doc/index.rst
doc/rg_yaff.rst
doc/rg_yaff_analysis.rst
doc/rg_yaff_conversion.rst
doc/rg_yaff_pes.rst
doc/rg_yaff_sampling.rst
doc/rg_yaff_tune.rst
doc/tu_silica.rst
doc/ug_analysis.rst
doc/ug_atselect.rst
doc/ug_cite.rst
doc/ug_features.rst
doc/ug_forcefield.rst
doc/ug_install.rst
doc/ug_overview.rst
doc/ug_sampling.rst
doc/ug_system.rst
doc/ug_troubles.rst
doc/ug_tune.rst
doc/_build/html/_images/backprop.png
doc/_build/html/_static/comment-bright.png
doc/_build/html/_static/comment-close.png
doc/_build/html/_static/comment.png
doc/_build/html/_static/down-pressed.png
doc/_build/html/_static/down.png
doc/_build/html/_static/file.png
doc/_build/html/_static/minus.png
doc/_build/html/_static/plus.png
doc/_build/html/_static/up-pressed.png
doc/_build/html/_static/up.png
scripts/yaff-opttest
yaff/__init__.py
yaff/atselect.py
yaff/log.py
yaff/system.py
yaff/version.py
yaff.egg-info/PKG-INFO
yaff.egg-info/SOURCES.txt
yaff.egg-info/dependency_links.txt
yaff.egg-info/not-zip-safe
yaff.egg-info/requires.txt
yaff.egg-info/top_level.txt
yaff/analysis/__init__.py
yaff/analysis/basic.py
yaff/analysis/blav.py
yaff/analysis/diffusion.py
yaff/analysis/hook.py
yaff/analysis/pca.py
yaff/analysis/rdf.py
yaff/analysis/spectrum.py
yaff/analysis/utils.py
yaff/analysis/test/__init__.py
yaff/analysis/test/common.py
yaff/analysis/test/test_basic.py
yaff/analysis/test/test_blav.py
yaff/analysis/test/test_diffusion.py
yaff/analysis/test/test_rdf.py
yaff/analysis/test/test_spectrum.py
yaff/conversion/__init__.py
yaff/conversion/common.py
yaff/conversion/cp2k.py
yaff/conversion/dlpoly.py
yaff/conversion/gaussian.py
yaff/conversion/xyz.py
yaff/conversion/test/__init__.py
yaff/conversion/test/test_cp2k.py
yaff/conversion/test/test_dlpoly.py
yaff/conversion/test/test_gaussian.py
yaff/conversion/test/test_xyz.py
yaff/data/opttest/DUBXXKHIPWMCDR-UHFFFAOYSA-N-pars-quickff.txt
yaff/data/opttest/DUBXXKHIPWMCDR-UHFFFAOYSA-N.chk
yaff/data/opttest/GZLNXARBGMAZKZ-KVFPUHGPSA-N-pars-quickff.txt
yaff/data/opttest/GZLNXARBGMAZKZ-KVFPUHGPSA-N.chk
