Metadata-Version: 1.1
Name: yaff
Version: 1.4.1
Summary: YAFF is yet another force-field code.
Home-page: http://molmod.ugent.be/code/
Author: Toon Verstraelen
Author-email: Toon.Verstraelen@UGent.be
License: UNKNOWN
Platform: UNKNOWN
Classifier: Environment :: Console
Classifier: License :: OSI Approved :: GNU General Public License v3 or later (GPLv3+)
Classifier: Operating System :: POSIX :: Linux
Classifier: Programming Language :: Python :: 2.7
Classifier: Programming Language :: Python :: 3
Classifier: Topic :: Scientific/Engineering :: Physics
Classifier: Topic :: Scientific/Engineering :: Chemistry
Classifier: Intended Audience :: Science/Research
